misosoupy/__init__.py
misosoupy/config.ini
misosoupy/import_sound_list.py
misosoupy/psychopy_exit_out.py
misosoupy/psychopy_present_instructions.py
misosoupy/psychopy_present_item_list.py
misosoupy/psychopy_refine_item_list.py
misosoupy/run_misosoupy.py
misosoupy/setup_misosoupy.py
misosoupy/skeleton.py
misosoupy/assets/FOAMS_sound_list.csv
misosoupy/assets/__init__.py
misosoupy/assets/naturalsounds165/stim102_crumpling_paper.wav
misosoupy/assets/naturalsounds165/stim103_crying.wav
misosoupy/assets/naturalsounds165/stim105_cutting_with_scissors.wav
misosoupy/assets/naturalsounds165/stim107_dial_tone.wav
misosoupy/assets/naturalsounds165/stim108_telephone_dialing.wav
misosoupy/assets/naturalsounds165/stim114_dishes_clanking.wav
misosoupy/assets/naturalsounds165/stim116_dog_barking.wav
misosoupy/assets/naturalsounds165/stim117_dog_drinking.wav
misosoupy/assets/naturalsounds165/stim118_puppy_whining.wav
misosoupy/assets/naturalsounds165/stim11_baby_crying.wav
misosoupy/assets/naturalsounds165/stim124_doorbell.wav
misosoupy/assets/naturalsounds165/stim12_background_speech.wav
misosoupy/assets/naturalsounds165/stim132_water_dripping.wav
misosoupy/assets/naturalsounds165/stim136_drum_roll.wav
misosoupy/assets/naturalsounds165/stim137_drum_solo.wav
misosoupy/assets/naturalsounds165/stim138_duck_quack.wav
misosoupy/assets/naturalsounds165/stim140_electric_hand_drill.wav
misosoupy/assets/naturalsounds165/stim150_finger_tapping.wav
misosoupy/assets/naturalsounds165/stim155_flag_flapping.wav
misosoupy/assets/naturalsounds165/stim156_wings_flapping.wav
misosoupy/assets/naturalsounds165/stim158_flushing.wav
misosoupy/assets/naturalsounds165/stim162_frog_croaking.wav
misosoupy/assets/naturalsounds165/stim163_frying.wav
misosoupy/assets/naturalsounds165/stim167_gargling.wav
misosoupy/assets/naturalsounds165/stim172_geese.wav
misosoupy/assets/naturalsounds165/stim174_girl_speaking.wav
misosoupy/assets/naturalsounds165/stim182_grunting_and_groaning.wav
misosoupy-0.1.3.dist-info/LICENSE.txt
misosoupy-0.1.3.dist-info/METADATA
misosoupy-0.1.3.dist-info/WHEEL
misosoupy-0.1.3.dist-info/top_level.txt
misosoupy-0.1.3.dist-info/RECORD
