Metadata-Version: 2.1
Name: misosoupy
Version: 0.1.3
Summary: Misophonia Stimuli Organization Using Python
Home-page: https://github.com/miso-sound/misosoupy/
Author: danibene
Author-email: 34680344+danibene@users.noreply.github.com
License: MIT
Project-URL: Documentation, https://pyscaffold.org/
Platform: any
Classifier: Development Status :: 4 - Beta
Classifier: Programming Language :: Python
Requires-Python: >=3.7
License-File: LICENSE.txt
Requires-Dist: importlib-metadata
Requires-Dist: importlib-resources
Requires-Dist: numpy
Requires-Dist: psychopy
Provides-Extra: testing
Requires-Dist: setuptools ; extra == 'testing'
Requires-Dist: pytest ; extra == 'testing'
Requires-Dist: pytest-cov ; extra == 'testing'
